{"cameraMode":{"drawMode":0,"name":"Shaded","section":"Shading Mode"},"sceneLighting":true,"audioPlay":false,"sceneViewState":{"showFog":true,"showMaterialUpdate":false,"showSkybox":true,"showFlares":true,"showImageEffects":true,"showParticleSystems":true},"in2DMode":false,"pivot":{"x":6.443337917327881,"y":-2.416613817214966,"z":13.882177352905274},"rotation":{"x":-0.016023656353354455,"y":0.9818106889724731,"z":-0.1631920486688614,"w":-0.09633602946996689},"size":121.32648468017578,"orthographic":false}